pypomes_core/.ruff.toml
pypomes_core/__init__.py
pypomes_core/datetime_pomes.py
pypomes_core/dict_pomes.py
pypomes_core/email_pomes.py
pypomes_core/encoding_pomes.py
pypomes_core/env_pomes.py
pypomes_core/file_pomes.py
pypomes_core/func_pomes.py
pypomes_core/list_pomes.py
pypomes_core/obj_pomes.py
pypomes_core/str_pomes.py
pypomes_core/validation_msgs.py
pypomes_core/validation_pomes.py
pypomes_core/xml_pomes.py
pypomes_core-2.9.9.dist-info/METADATA
pypomes_core-2.9.9.dist-info/WHEEL
pypomes_core-2.9.9.dist-info/licenses/LICENSE
pypomes_core-2.9.9.dist-info/RECORD
