Metadata-Version: 2.4
Name: pypomes_core
Version: 2.9.9
Summary: A collection of Python pomes, penyeach (core modules)
Project-URL: Homepage, https://github.com/TheWiseCoder/PyPomes-Core
Project-URL: Bug Tracker, https://github.com/TheWiseCoder/PyPomes-Core/issues
Author-email: GT Nunes <wisecoder01@gmail.com>
License-File: LICENSE
Classifier: License :: OSI Approved :: MIT License
Classifier: Operating System :: OS Independent
Classifier: Programming Language :: Python :: 3
Requires-Python: >=3.14
Requires-Dist: filetype>=1.2.0
Requires-Dist: puremagic>=1.30
Requires-Dist: python-dateutil>=2.9.0
Requires-Dist: tzdata>=2025.3
Requires-Dist: xmltodict3>=0.0.4
